[
  {
    "id": 1,
    "location": "Aimana mana",
    "picName": "Nama orang",
    "email": "Nama@gmail.com",
    "phone": "081816032859",
    "dryingMachines": 3,
    "flouringMachines": 1
  },
  {
    "id": 2,
    "location": "Dimana mana",
    "picName": "Nama orang",
    "email": "Nama@gmail.com",
    "phone": "082816032859",
    "dryingMachines": 3,
    "flouringMachines": 1
  },
  {
    "id": 3,
    "location": "Dimana mana",
    "picName": "Nama orang",
    "email": "Nama@gmail.com",
    "phone": "082816032859",
    "dryingMachines": 3,
    "flouringMachines": 1
  },
  {
    "id": 4,
    "location": "Dimana mana",
    "picName": "Nama orang",
    "email": "Nama@gmail.com",
    "phone": "082816032859",
    "dryingMachines": 3,
    "flouringMachines": 1
  },
  {
    "id": 5,
    "location": "Dimana mana",
    "picName": "Nama orang",
    "email": "Nama@gmail.com",
    "phone": "082816032859",
    "dryingMachines": 3,
    "flouringMachines": 1
  },
  {
    "id": 6,
    "location": "Dimana mana",
    "picName": "Nama orang",
    "email": "Nama@gmail.com",
    "phone": "082816032859",
    "dryingMachines": 3,
    "flouringMachines": 1
  },
  {
    "id": 7,
    "location": "Dimana mana",
    "picName": "Nama orang",
    "email": "Nama@gmail.com",
    "phone": "082816032859",
    "dryingMachines": 3,
    "flouringMachines": 1
  }
]
